README.rst
pelican_hot.py
setup.py
pelican_hot.egg-info/PKG-INFO
pelican_hot.egg-info/SOURCES.txt
pelican_hot.egg-info/dependency_links.txt
pelican_hot.egg-info/requires.txt
pelican_hot.egg-info/top_level.txt