Metadata-Version: 1.1
Name: pelican_hot
Version: 0.1
Summary: A Pelican plugin to make a list of hot posts by social media.
Home-page: https://github.com/wutali/pelican_hot
Author: Takahiro Fujiwara
Author-email: email@wuta.li
License: UNKNOWN
Download-URL: https://github.com/wutali/pelican_hot/tarball/master
Platform: UNKNOWN
